simply_pypi_search/__init__.py
simply_pypi_search-1.3.1.dist-info/LICENSE.txt
simply_pypi_search-1.3.1.dist-info/METADATA
simply_pypi_search-1.3.1.dist-info/WHEEL
simply_pypi_search-1.3.1.dist-info/top_level.txt
simply_pypi_search-1.3.1.dist-info/RECORD
