Metadata-Version: 2.1
Name: simply-pypi-search
Version: 1.3.1
Summary: A simply tool to search for packages on pypi.org
Home-page: https://github.com/mccoderpy/simply-pypi-search
Author: mccoder.py
Author-email: mccuber04@outlook.de
License: MIT
Project-URL: Source, https://github.com/mccoderpy/simply-pypi-search
Platform: UNKNOWN
Classifier: License :: OSI Approved :: MIT License
Classifier: Programming Language :: Python :: 3
Classifier: Programming Language :: Python :: 3.9
Requires-Python: >=3.6
Requires-Dist: aiohttp
Requires-Dist: bs4
